proyecto_deploy/__init__.py
proyecto_deploy-0.0.1.dist-info/METADATA
proyecto_deploy-0.0.1.dist-info/WHEEL
proyecto_deploy-0.0.1.dist-info/top_level.txt
proyecto_deploy-0.0.1.dist-info/RECORD
