Metadata-Version: 2.4
Name: proyecto-deploy
Version: 0.0.1
Summary: Deployment phase package (CRISP-DM)
Author: Angel Castellanos, Alejandro Azurdia, Diego Morales
Requires-Python: >=3.8
Requires-Dist: proyecto-core==0.0.1
Requires-Dist: joblib>=1.2.0
Requires-Dist: pandas>=2.0.0
Dynamic: author
Dynamic: requires-dist
Dynamic: requires-python
Dynamic: summary
